wei/__init__.py
wei/smtp.py
wei/zulip.py
wei-1.11.dist-info/METADATA
wei-1.11.dist-info/WHEEL
wei-1.11.dist-info/top_level.txt
wei-1.11.dist-info/RECORD
