Metadata-Version: 2.1
Name: wei
Version: 1.11
Summary: Email and Zulip Notifications
License: MIT
Classifier: Programming Language :: Python :: 3
Classifier: License :: OSI Approved :: MIT License
Classifier: Operating System :: OS Independent
Requires-Python: >=3.6
Requires-Dist: requests (>=2.0)
